improf.py
improf-0.2.1.dist-info/LICENSE
improf-0.2.1.dist-info/METADATA
improf-0.2.1.dist-info/WHEEL
improf-0.2.1.dist-info/entry_points.txt
improf-0.2.1.dist-info/top_level.txt
improf-0.2.1.dist-info/RECORD
