Metadata-Version: 2.1
Name: improf
Version: 0.2.1
Summary: The import profiler
Home-page: https://github.com/effigies/improf
Author: Christopher J. Markiewicz
Author-email: effigies@gmail.com
License: GPLv3
Classifier: Development Status :: 4 - Beta
Classifier: Environment :: Console
Classifier: Intended Audience :: Developers
Classifier: License :: OSI Approved :: GNU General Public License v3 (GPLv3)
Classifier: Operating System :: OS Independent
Classifier: Programming Language :: Python :: 3
Classifier: Topic :: Software Development
License-File: LICENSE
Requires-Dist: psutil
